setup.py
pysiriproxy/__init__.py
pysiriproxy/constants.py
pysiriproxy/interpreter.py
pysiriproxy/packetPlayer.py
pysiriproxy/plist.py
pysiriproxy/utils.py
pysiriproxy.egg-info/PKG-INFO
pysiriproxy.egg-info/SOURCES.txt
pysiriproxy.egg-info/dependency_links.txt
pysiriproxy.egg-info/requires.txt
pysiriproxy.egg-info/top_level.txt
pysiriproxy/connections/__init__.py
pysiriproxy/connections/connection.py
pysiriproxy/connections/iphone.py
pysiriproxy/connections/manager.py
pysiriproxy/connections/server.py
pysiriproxy/objects/__init__.py
pysiriproxy/objects/actions.py
pysiriproxy/objects/baseObject.py
pysiriproxy/objects/buttons.py
pysiriproxy/objects/commands.py
pysiriproxy/objects/dataObjects.py
pysiriproxy/objects/factory.py
pysiriproxy/objects/requests.py
pysiriproxy/objects/views.py
pysiriproxy/options/__init__.py
pysiriproxy/options/config.py
pysiriproxy/options/options.py
pysiriproxy/plugins/__init__.py
pysiriproxy/plugins/directions.py
pysiriproxy/plugins/manager.py
pysiriproxy/plugins/objectClasses.py
pysiriproxy/plugins/plugin.py
pysiriproxy/plugins/responses.py
pysiriproxy/plugins/speechRules.py
pysiriproxy/testing/__init__.py
pysiriproxy/testing/pluginTester.py
pysiriproxy/testing/testSupport.py